paper2txt/__init__.py
paper2txt/executable.py
paper2txt-0.0.4.dist-info/LICENSE
paper2txt-0.0.4.dist-info/WHEEL
paper2txt-0.0.4.dist-info/entry_points.txt
paper2txt-0.0.4.dist-info/METADATA
paper2txt-0.0.4.dist-info/RECORD
